scrapy_save_as_pdf/__init__.py
scrapy_save_as_pdf/pipelines.py
scrapy_save_as_pdf-0.2.1.dist-info/METADATA
scrapy_save_as_pdf-0.2.1.dist-info/WHEEL
scrapy_save_as_pdf-0.2.1.dist-info/top_level.txt
scrapy_save_as_pdf-0.2.1.dist-info/RECORD
